m10s/__init__.py
m10s/density.py
m10s/length.py
m10s/mass.py
m10s/utils.py
m10s/volume.py
m10s-0.1.0.dist-info/METADATA
m10s-0.1.0.dist-info/WHEEL
m10s-0.1.0.dist-info/top_level.txt
m10s-0.1.0.dist-info/RECORD
